djangorestframework_fsm/__init__.py
djangorestframework_fsm/viewset_mixins.py
djangorestframework_fsm-0.1.2.dist-info/LICENSE
djangorestframework_fsm-0.1.2.dist-info/METADATA
djangorestframework_fsm-0.1.2.dist-info/WHEEL
djangorestframework_fsm-0.1.2.dist-info/top_level.txt
djangorestframework_fsm-0.1.2.dist-info/RECORD
