Metadata-Version: 2.1
Name: djangorestframework-fsm
Version: 0.1.2
Summary: Automatically hook your Django-FSM transitions up to Django REST Framework
Home-page: https://github.com/27medkamal/djangorestframework-fsm
Author: Ahmed Kamal
Author-email: 27madkamal@gmail.com
License: UNKNOWN
Platform: UNKNOWN
Requires-Dist: django
Requires-Dist: django-fsm
Requires-Dist: djangorestframework
